<?xml version="1.0"?>
<odoo>
    <data>

        <!-- Smileys -->
        <record id="mail_smiley_grinning_face" model="mail.shortcode">
            <field name="source">:grinning:</field>
            <field name="unicode_source">😀</field>
            <field name="substitution">&lt;img src='/mail/static/src/img/smiley/grinning_face.png' alt='😀'/&gt;</field>
            <field name="description">Grinning Face</field>
            <field name="shortcode_type">image</field>
        </record>

    </data>
</odoo>
